{
  "best_global_step": 680,
  "best_metric": 0.3813547194004059,
  "best_model_checkpoint": "model\\checkpoint-680",
  "epoch": 10.0,
  "eval_steps": 500,
  "global_step": 1360,
  "is_hyper_param_search": false,
  "is_local_process_zero": true,
  "is_world_process_zero": true,
  "log_history": [
    {
      "epoch": 0.7352941176470589,
      "grad_norm": 17.892513275146484,
      "learning_rate": 7.317073170731707e-06,
      "loss": 1.6216,
      "step": 100
    },
    {
      "epoch": 1.0,
      "eval_accuracy": 0.7029520295202952,
      "eval_f1": 0.6965671672928669,
      "eval_loss": 0.8381209373474121,
      "eval_runtime": 34.65,
      "eval_samples_per_second": 15.642,
      "eval_steps_per_second": 1.962,
      "step": 136
    },
    {
      "epoch": 1.4705882352941178,
      "grad_norm": 11.440704345703125,
      "learning_rate": 1.4708056171470807e-05,
      "loss": 0.8262,
      "step": 200
    },
    {
      "epoch": 2.0,
      "eval_accuracy": 0.8394833948339483,
      "eval_f1": 0.834044144276424,
      "eval_loss": 0.44589880108833313,
      "eval_runtime": 23.7546,
      "eval_samples_per_second": 22.817,
      "eval_steps_per_second": 2.863,
      "step": 272
    },
    {
      "epoch": 2.2058823529411766,
      "grad_norm": 13.13448429107666,
      "learning_rate": 2.2099039172209902e-05,
      "loss": 0.4781,
      "step": 300
    },
    {
      "epoch": 2.9411764705882355,
      "grad_norm": 17.663497924804688,
      "learning_rate": 2.9490022172949004e-05,
      "loss": 0.3918,
      "step": 400
    },
    {
      "epoch": 3.0,
      "eval_accuracy": 0.8357933579335793,
      "eval_f1": 0.8294348815136031,
      "eval_loss": 0.4455364942550659,
      "eval_runtime": 23.654,
      "eval_samples_per_second": 22.914,
      "eval_steps_per_second": 2.875,
      "step": 408
    },
    {
      "epoch": 3.6764705882352944,
      "grad_norm": 6.804754734039307,
      "learning_rate": 3.6881005173688106e-05,
      "loss": 0.2945,
      "step": 500
    },
    {
      "epoch": 4.0,
      "eval_accuracy": 0.8468634686346863,
      "eval_f1": 0.8476654730538562,
      "eval_loss": 0.4447120130062103,
      "eval_runtime": 23.555,
      "eval_samples_per_second": 23.01,
      "eval_steps_per_second": 2.887,
      "step": 544
    },
    {
      "epoch": 4.411764705882353,
      "grad_norm": 15.030138969421387,
      "learning_rate": 4.4271988174427204e-05,
      "loss": 0.3229,
      "step": 600
    },
    {
      "epoch": 5.0,
      "eval_accuracy": 0.8745387453874539,
      "eval_f1": 0.8715794966777145,
      "eval_loss": 0.3813547194004059,
      "eval_runtime": 23.5754,
      "eval_samples_per_second": 22.99,
      "eval_steps_per_second": 2.884,
      "step": 680
    },
    {
      "epoch": 5.147058823529412,
      "grad_norm": 24.0283203125,
      "learning_rate": 5.1662971175166295e-05,
      "loss": 0.3049,
      "step": 700
    },
    {
      "epoch": 5.882352941176471,
      "grad_norm": 20.851341247558594,
      "learning_rate": 5.90539541759054e-05,
      "loss": 0.2822,
      "step": 800
    },
    {
      "epoch": 6.0,
      "eval_accuracy": 0.8560885608856088,
      "eval_f1": 0.8573569573707319,
      "eval_loss": 0.444107323884964,
      "eval_runtime": 23.5412,
      "eval_samples_per_second": 23.023,
      "eval_steps_per_second": 2.889,
      "step": 816
    },
    {
      "epoch": 6.617647058823529,
      "grad_norm": 12.900912284851074,
      "learning_rate": 6.644493717664449e-05,
      "loss": 0.2761,
      "step": 900
    },
    {
      "epoch": 7.0,
      "eval_accuracy": 0.8634686346863468,
      "eval_f1": 0.8597130650757173,
      "eval_loss": 0.45554402470588684,
      "eval_runtime": 23.5447,
      "eval_samples_per_second": 23.02,
      "eval_steps_per_second": 2.888,
      "step": 952
    },
    {
      "epoch": 7.352941176470588,
      "grad_norm": 29.883827209472656,
      "learning_rate": 7.38359201773836e-05,
      "loss": 0.3015,
      "step": 1000
    },
    {
      "epoch": 8.0,
      "eval_accuracy": 0.8357933579335793,
      "eval_f1": 0.8355974752152496,
      "eval_loss": 0.5341833829879761,
      "eval_runtime": 23.6406,
      "eval_samples_per_second": 22.927,
      "eval_steps_per_second": 2.876,
      "step": 1088
    },
    {
      "epoch": 8.088235294117647,
      "grad_norm": 18.2558536529541,
      "learning_rate": 8.122690317812269e-05,
      "loss": 0.2692,
      "step": 1100
    },
    {
      "epoch": 8.823529411764707,
      "grad_norm": 10.86754322052002,
      "learning_rate": 8.86178861788618e-05,
      "loss": 0.3024,
      "step": 1200
    },
    {
      "epoch": 9.0,
      "eval_accuracy": 0.8321033210332104,
      "eval_f1": 0.8285866035834304,
      "eval_loss": 0.6181555986404419,
      "eval_runtime": 23.6337,
      "eval_samples_per_second": 22.933,
      "eval_steps_per_second": 2.877,
      "step": 1224
    },
    {
      "epoch": 9.558823529411764,
      "grad_norm": 4.158212184906006,
      "learning_rate": 9.600886917960089e-05,
      "loss": 0.2851,
      "step": 1300
    },
    {
      "epoch": 10.0,
      "eval_accuracy": 0.8487084870848709,
      "eval_f1": 0.8466562665813026,
      "eval_loss": 0.467192143201828,
      "eval_runtime": 23.633,
      "eval_samples_per_second": 22.934,
      "eval_steps_per_second": 2.877,
      "step": 1360
    },
    {
      "epoch": 10.0,
      "step": 1360,
      "total_flos": 1.6770446528403456e+18,
      "train_loss": 0.4530462321113138,
      "train_runtime": 2153.2015,
      "train_samples_per_second": 50.274,
      "train_steps_per_second": 3.158
    }
  ],
  "logging_steps": 100,
  "max_steps": 6800,
  "num_input_tokens_seen": 0,
  "num_train_epochs": 50,
  "save_steps": 500,
  "stateful_callbacks": {
    "EarlyStoppingCallback": {
      "args": {
        "early_stopping_patience": 5,
        "early_stopping_threshold": 0.001
      },
      "attributes": {
        "early_stopping_patience_counter": 5
      }
    },
    "TrainerControl": {
      "args": {
        "should_epoch_stop": false,
        "should_evaluate": false,
        "should_log": false,
        "should_save": true,
        "should_training_stop": true
      },
      "attributes": {}
    }
  },
  "total_flos": 1.6770446528403456e+18,
  "train_batch_size": 16,
  "trial_name": null,
  "trial_params": null
}
